<annotation>
	<folder>tires-data</folder>
	<filename>19.FVUVMBWGT6ZDWZW.LARGE.jpg</filename>
	<path>/home/tjensen/datasets/tires-data/19.FVUVMBWGT6ZDWZW.LARGE.jpg</path>
	<source>
		<database>Unknown</database>
	</source>
	<size>
		<width>450</width>
		<height>300</height>
		<depth>3</depth>
	</size>
	<segmented>0</segmented>
	<object>
		<name>tire</name>
		<pose>Unspecified</pose>
		<truncated>0</truncated>
		<difficult>0</difficult>
		<bndbox>
			<xmin>69</xmin>
			<ymin>18</ymin>
			<xmax>384</xmax>
			<ymax>288</ymax>
		</bndbox>
	</object>
</annotation>
